ray_utils/__init__.py
ray_utils/_apply_parallel.py
ray_utils/_init_in_context.py
ray_utils-0.0.5.dist-info/METADATA
ray_utils-0.0.5.dist-info/WHEEL
ray_utils-0.0.5.dist-info/licenses/LICENSE
ray_utils-0.0.5.dist-info/RECORD
