Metadata-Version: 2.3
Name: ray-utils
Version: 0.0.5
Summary: utility functions for https://github.com/ray-project/ray/
Project-URL: Homepage, https://github.com/shadiakiki1986/ray-utils
Project-URL: Issues, https://github.com/shadiakiki1986/ray-utils/issues
Author-email: Shadi Akiki <shadi@akiki.us>
License-File: LICENSE
Classifier: License :: OSI Approved :: MIT License
Classifier: Operating System :: OS Independent
Classifier: Programming Language :: Python :: 3
Requires-Python: >=3.8
